{"stateId":"goa","places":[{"id":"baga-beach","name":"Baga Beach","slug":"baga-beach","district":"north-goa","thumbnail":"","rating":4.5,"reviewCount":15000,"category":"beaches","shortDescription":"Famous for water sports, nightlife, and vibrant beach shacks","popularityScore":94,"priceLevel":2},{"id":"goa-palolem-beach","name":"Palolem Beach","slug":"goa-palolem-beach","district":"south-goa","thumbnail":"","rating":4.7,"reviewCount":12000,"category":"beaches","shortDescription":"A crescent-shaped beach paradise with calm waters","popularityScore":92,"priceLevel":2},{"id":"basilica-bom-jesus","name":"Basilica of Bom Jesus","slug":"basilica-bom-jesus","district":"north-goa","thumbnail":"","rating":4.6,"reviewCount":8000,"category":"heritage","shortDescription":"16th century UNESCO World Heritage church","popularityScore":85,"priceLevel":1}]}
