{
  "id": "machail-mata",
  "name": "Machail Mata Shrine",
  "city": "Kishtwar",
  "state": "Jammu and Kashmir",
  "description": "An incredibly remote and highly revered Hindu shrine dedicated to Goddess Chandi. It requires a strenuous multi-day trek through breathtaking Himalayan landscapes.",
  "history": "The annual Chhadi Yatra (mace procession) attracts tens of thousands of devotees who travel from Jammu to this remote Kishtwar valley.",
  "famousFor": "Strenuous pilgrimage trek, Paddar sapphire mines nearby, Goddess Chandi.",
  "bestTime": "August (During the Yatra)",
  "timings": "Open 24/7 (Summer only)",
  "entryFee": "Free (Helicopter available during Yatra)",
  "image": "./assets/images/states/jammu-and-kashmir/machail-mata.webp",
  "heroImage": "./assets/images/states/jammu-and-kashmir/machail-mata.webp",
  "gallery": [
    "./assets/images/states/jammu-and-kashmir/machail-mata.webp"
  ],
  "nearbyPlaces": [
    "nishat-bagh",
    "shiv-khori",
    "shalimar-bagh",
    "yusmarg",
    "dachigam-national-park",
    "doodhpathri",
    "pari-mahal",
    "manasbal-lake",
    "bhaderwah",
    "kheer-bhawani",
    "naranag",
    "aharbal-waterfall",
    "dal-lake",
    "chashma-shahi",
    "drung-waterfall",
    "shankaracharya-temple",
    "hari-parbat",
    "gurez-valley",
    "wular-lake",
    "bangus-valley",
    "awantipora-ruins",
    "hazratbal-shrine",
    "habba-khatoon",
    "peer-ki-gali",
    "nigeen-lake",
    "lolab-valley"
  ]
}