{
  "id": "taj-ul-masajid",
  "name": "Taj-ul-Masajid",
  "city": "Bhopal",
  "state": "Madhya Pradesh",
  "description": "One of the largest mosques in Asia, its name literally translates to 'Crown Among Mosques'. It features pink bricks, massive domes, and towering minarets.",
  "history": "Construction was started by Nawab Shah Jahan Begum of Bhopal (1868–1901) and was finally completed in 1985.",
  "famousFor": "Massive architecture, pink facade, and spiritual significance.",
  "bestTime": "October to March",
  "timings": "6:00 AM – 8:00 PM",
  "entryFee": "Free",
  "image": "./assets/images/states/madhya-pradesh/Taj-ul-Masajid.webp",
  "heroImage": "./assets/images/states/madhya-pradesh/Taj-ul-Masajid.webp",
  "gallery": [
    "./assets/images/states/madhya-pradesh/Taj-ul-Masajid.webp"
  ],
  "nearbyPlaces": [
    "asirgarh-fort",
    "dhar-fort",
    "chanderi",
    "shahi-qila",
    "hanuwantiya-island",
    "maiha-sharda-temple",
    "kanha-national-park",
    "govindgarh-palace",
    "madhav-national-park",
    "fossil-national-park",
    "bhimkund",
    "mitawali-temple",
    "sonagiri-jain-temples",
    "bandhavgarh-national-park",
    "panna-national-park",
    "chaman-mahal-islamnagar",
    "kuno-national-park",
    "bahuti-falls",
    "bhopal-upper-lake",
    "heliodorus-pillar",
    "kakanmath-temple",
    "chitrakoot",
    "bhojpur-temple",
    "bhimbetka-rock-shelters",
    "van-vihar-national-park",
    "muktagiri",
    "rewa-fort",
    "datia-palace",
    "ken-gharial-sanctuary",
    "pashupatinath-temple",
    "pench-national-park",
    "bateshwar-temples-morena",
    "ramnagar-fort",
    "raisen-fort",
    "dargah-e-hakimi"
  ]
}
